league/__init__.py
league/client.py
league/handler.py
league/lexicon.py
league/objects/__init__.py
league/objects/account.py
league/objects/cache.py
league/objects/character.py
league/objects/item.py
league/objects/spell.py
league-0.0.2.dist-info/LICENSE
league-0.0.2.dist-info/METADATA
league-0.0.2.dist-info/WHEEL
league-0.0.2.dist-info/top_level.txt
league-0.0.2.dist-info/RECORD
